vibe_pentesterlab/__init__.py
vibe_pentesterlab/cli.py
vibe_pentesterlab-2.0.1.dist-info/METADATA
vibe_pentesterlab-2.0.1.dist-info/WHEEL
vibe_pentesterlab-2.0.1.dist-info/entry_points.txt
vibe_pentesterlab-2.0.1.dist-info/top_level.txt
vibe_pentesterlab-2.0.1.dist-info/RECORD
