Metadata-Version: 2.4
Name: vibe-pentesterlab
Version: 2.0.1
Summary: AI-Assisted Offensive Security Framework
Home-page: https://github.com/kcprajeesh/vibe-pentesterlab
Author: Prajeesh KC
Author-email: vp.prajeesh2@gmail.com
Classifier: Programming Language :: Python :: 3
Classifier: License :: OSI Approved :: MIT License
Classifier: Operating System :: OS Independent
Requires-Python: >=3.8
Dynamic: author
Dynamic: author-email
Dynamic: classifier
Dynamic: description
Dynamic: description-content-type
Dynamic: home-page
Dynamic: requires-python
Dynamic: summary
